{"_type":"export","__export_format":4,"__export_date":"2024-03-04T04:37:27.557Z","__export_source":"insomnia.desktop.app:v2023.5.8","resources":[{"_id":"req_e57c6bda577e4655bd3dbbf4aa4c7036","parentId":"wrk_e41a82afad664f22b7113566510f59d5","modified":1709522861305,"created":1709522833156,"url":"{{baseUrl}}/products","name":"List Products","description":"Método que traz a lista de produtos cadastrados","method":"GET","body":{},"parameters":[],"headers":[{"name":"User-Agent","value":"insomnia/2023.5.8"}],"authentication":{},"metaSortKey":-1709522833156,"isPrivate":false,"settingStoreCookies":true,"settingSendCookies":true,"settingDisableRenderRequestBody":false,"settingEncodeUrl":true,"settingRebuildPath":true,"settingFollowRedirects":"global","_type":"request"},{"_id":"wrk_e41a82afad664f22b7113566510f59d5","parentId":null,"modified":1709445645756,"created":1709445645756,"name":"test-api","description":"","scope":"collection","_type":"workspace"},{"_id":"req_ce6e455070a048cbadcc968111a72879","parentId":"wrk_e41a82afad664f22b7113566510f59d5","modified":1709526952040,"created":1709445733996,"url":"{{baseUrl}}/sales","name":"List Sales","description":"Esse endpoint irá trazer os dados das vendas","method":"GET","body":{},"parameters":[],"headers":[{"name":"User-Agent","value":"insomnia/2023.5.8"}],"authentication":{},"metaSortKey":-1708688549551.5,"isPrivate":false,"settingStoreCookies":true,"settingSendCookies":true,"settingDisableRenderRequestBody":false,"settingEncodeUrl":true,"settingRebuildPath":true,"settingFollowRedirects":"global","_type":"request"},{"_id":"req_a57e01fa47af44ca8f7a68554c1ff6f9","parentId":"wrk_e41a82afad664f22b7113566510f59d5","modified":1709527017918,"created":1709518492228,"url":"{{baseUrl}}/sales","name":"Create Sale","description":"Cria uma nova venda","method":"POST","body":{"mimeType":"application/json","text":"{\n\t\"products\": [\n\t\t{\n\t\t\t\"id\": 1,\n\t\t\t\"amount\": 2\n\t\t}\n\t]\n}"},"parameters":[],"headers":[{"name":"Content-Type","value":"application/json"},{"name":"User-Agent","value":"insomnia/2023.5.8"}],"authentication":{},"metaSortKey":-1708593912214.4375,"isPrivate":false,"settingStoreCookies":true,"settingSendCookies":true,"settingDisableRenderRequestBody":false,"settingEncodeUrl":true,"settingRebuildPath":true,"settingFollowRedirects":"global","_type":"request"},{"_id":"req_14dd7a38632e4f33ba397078d7081694","parentId":"wrk_e41a82afad664f22b7113566510f59d5","modified":1709526965959,"created":1709520742203,"url":"{{baseUrl}}/sales/8","name":"Get Sale","description":"Recupera os dados de uma venda","method":"GET","body":{},"parameters":[],"headers":[{"name":"User-Agent","value":"insomnia/2023.5.8"}],"authentication":{},"metaSortKey":-1708499274877.375,"isPrivate":false,"settingStoreCookies":true,"settingSendCookies":true,"settingDisableRenderRequestBody":false,"settingEncodeUrl":true,"settingRebuildPath":true,"settingFollowRedirects":"global","_type":"request"},{"_id":"req_37513e745782456a8c683c94d7c14f56","parentId":"wrk_e41a82afad664f22b7113566510f59d5","modified":1709526973626,"created":1709522367009,"url":"{{baseUrl}}/sales/8/cancel","name":"Cancel Sale","description":"Cancela uma venda","method":"PUT","body":{},"parameters":[],"headers":[{"name":"User-Agent","value":"insomnia/2023.5.8"}],"authentication":{},"metaSortKey":-1708404637540.3125,"isPrivate":false,"settingStoreCookies":true,"settingSendCookies":true,"settingDisableRenderRequestBody":false,"settingEncodeUrl":true,"settingRebuildPath":true,"settingFollowRedirects":"global","_type":"request"},{"_id":"req_4e3f8645b0184c8489203a86a9cbfccb","parentId":"wrk_e41a82afad664f22b7113566510f59d5","modified":1709527004312,"created":1709523377146,"url":"{{baseUrl}}/sales/1","name":"Add Products To Sale","description":"Adiciona um novo produto a venda.\n\nObs.: se o produto ja estiver na venda, apeans a quantidade será alterada.","method":"PUT","body":{"mimeType":"application/json","text":"{\n\t\"products\": [\n\t\t{\n\t\t\t\"id\": 5,\n\t\t\t\"amount\": 1\n\t\t}\n\t]\n}"},"parameters":[],"headers":[{"name":"Content-Type","value":"application/json"},{"name":"User-Agent","value":"insomnia/2023.5.8"}],"authentication":{},"metaSortKey":-1708357318871.7812,"isPrivate":false,"settingStoreCookies":true,"settingSendCookies":true,"settingDisableRenderRequestBody":false,"settingEncodeUrl":true,"settingRebuildPath":true,"settingFollowRedirects":"global","_type":"request"},{"_id":"env_3aaa9f2d13a4f5c5c5f3f625de59aefb8e67a1a2","parentId":"wrk_e41a82afad664f22b7113566510f59d5","modified":1709445712774,"created":1709445645759,"name":"Base Environment","data":{"baseUrl":"http://localhost:8000/api"},"dataPropertyOrder":{"&":["baseUrl"]},"color":null,"isPrivate":false,"metaSortKey":1709445645759,"_type":"environment"},{"_id":"jar_3aaa9f2d13a4f5c5c5f3f625de59aefb8e67a1a2","parentId":"wrk_e41a82afad664f22b7113566510f59d5","modified":1709445645760,"created":1709445645760,"name":"Default Jar","cookies":[],"_type":"cookie_jar"}]}